odoo10_addon_account_analytic_sequence-10.0.1.0.0-py2.7-nspkg.pth
odoo/addons/account_analytic_sequence/README.rst
odoo/addons/account_analytic_sequence/__init__.py
odoo/addons/account_analytic_sequence/__manifest__.py
odoo/addons/account_analytic_sequence/data/sequence.xml
odoo/addons/account_analytic_sequence/models/__init__.py
odoo/addons/account_analytic_sequence/models/account_analytic_account.py
odoo/addons/account_analytic_sequence/static/description/icon.png
odoo10_addon_account_analytic_sequence-10.0.1.0.0.dist-info/DESCRIPTION.rst
odoo10_addon_account_analytic_sequence-10.0.1.0.0.dist-info/METADATA
odoo10_addon_account_analytic_sequence-10.0.1.0.0.dist-info/RECORD
odoo10_addon_account_analytic_sequence-10.0.1.0.0.dist-info/WHEEL
odoo10_addon_account_analytic_sequence-10.0.1.0.0.dist-info/metadata.json
odoo10_addon_account_analytic_sequence-10.0.1.0.0.dist-info/namespace_packages.txt
odoo10_addon_account_analytic_sequence-10.0.1.0.0.dist-info/top_level.txt
